sphinxx/__init__.py
sphinxx-0.1.1.dist-info/licenses/LICENSE.txt
sphinxx-0.1.1.dist-info/METADATA
sphinxx-0.1.1.dist-info/WHEEL
sphinxx-0.1.1.dist-info/top_level.txt
sphinxx-0.1.1.dist-info/RECORD
